setup.py
develia/__init__.py
develia/toolkit/__init__.py
develia/toolkit/_cachediterable.py
develia/toolkit/_functions.py
develia/toolkit/_iterablegeneratorfn.py
develia/toolkit/_iteratorhandler.py
develia/toolkit/_lazy.py
develia/toolkit/_segment.py
develia/toolkit/_stream.py
develia/toolkit/arraytools.py
develia/toolkit/concurrency.py
develia/toolkit/datetools.py
develia/toolkit/math.py
develia/toolkit/parser.py
develia_toolkit.egg-info/PKG-INFO
develia_toolkit.egg-info/SOURCES.txt
develia_toolkit.egg-info/dependency_links.txt
develia_toolkit.egg-info/top_level.txt